Workbook
Name Slicer_Account_Type: #N/A
Name Slicer_KYC_Status: #N/A

Sheet Raw Data
A1: Full Name | B1: Username | C1: Account Type | D1: Country | E1: City | F1: Age | G1: Gender | H1: Email | I1: Phone Number | J1: Account Creation Date | K1: Last Active Date | L1: Balance (USD) | M1: Debt (USD) | N1: Credit Score | O1: Income Level (USD Annual) | P1: Risk Category | Q1: KYC Status | R1: Fraud Flag | S1: Account Status
A2: Carlos M. Rivera Jr. | B2: carlos_rivera23 | C2: Premium | D2: US | E2: New York | F2: 42 | G2: Male | H2: carlos.rivera23@email.com | I2: =1-718-555-199 -> -1471 | J2: 43539 | K2: 45303 | L2: 45250.75 | M2: 12500.5 | N2: 745 | O2: 85000 | P2: Medium | Q2: Verified | R2: 0 | S2: Active
A3: Aiko Tanaka | B3: aiko_tanaka | C3: Digital-Only | D3: Japan | E3: Tokyo | F3: 28 | G3: Female | H3: aiko.tanaka@mail.jp | I3: =81-90-1234-5678 -> -6921 | J3: 44764 | K3: 45305 | L3: 12800 | M3: 3500.25 | N3: 810 | O3: 45000 | P3: Low | Q3: Verified | R3: 0 | S3: Active
A4: Md. Rahim Uddin | B4: rahim_uddin | C4: Business | D4: India | E4: Mumbai | F4: 35 | G4: Male | H4: rahim.uddin@business.in | I4: =91-987-654-3210 -> -4760 | J4: 44140 | K4: 45301 | L4: 87500.8 | M4: 45000.75 | N4: 680 | O4: 120000 | P4: Medium | Q4: Pending | R4: 0 | S4: Active
A5: Anna-Louise Clarke | B5: anna_clarke | C5: Joint | D5: UK | E5: London | F5: 31 | G5: Female | H5: anna.clarke@email.co.uk | I5: =44-20-7946-958 -> -8880 | J5: 44457 | K5: 45304 | L5: 25600.3 | M5: 18000 | N5: 720 | O5: 75000 | P5: Low | Q5: Verified | R5: 0 | S5: Active
A6: John 'Jack' Thompson | B6: jack_thompson | C6: Savings | D6: US | E6: Chicago | F6: 45 | G6: Male | H6: jack.thompson@email.com | I6: =1-312-555-123 -> -989 | J6: 43250 | K6: 45302 | L6: 67500.45 | M6: 25000.8 | N6: 695 | O6: 95000 | P6: Medium | Q6: Verified | R6: 0 | S6: Active
A7: Wei Zhang | B7: wei_zhang95 | C7: Current | D7: China | E7: Shanghai | F7: 26 | G7: Male | H7: wei.zhang@mail.cn | I7: =86-138-13-8000 -> -8065 | J7: 44971 | K7: 45306 | L7: 9800.25 | M7: 4200.5 | N7: 780 | O7: 38000 | P7: Low | Q7: Verified | R7: 0 | S7: Active
A8: Maria Silva Santos | B8: maria_silva | C8: Savings | D8: Brazil | E8: SÃ£o Paulo | F8: 39 | G8: Female | H8: maria.santos@email.com.br | I8: =55-11-91234-5678 -> -96868 | J8: 43689 | K8: 45300 | L8: 32400.6 | M8: 15800.25 | N8: 710 | O8: 68000 | P8: Medium | Q8: Verified | R8: 0 | S8: Active
A9: Chiamaka Okoro | B9: chiamaka_o | C9: Digital-Only | D9: Nigeria | E9: Lagos | F9: 24 | G9: Female | H9: chiamaka.okoro@mail.ng | I9: =234-703-456-7890 -> -8815 | J9: 45066 | K9: 45305 | L9: 5600.75 | M9: 3200 | N9: 650 | O9: 29000 | P9: Medium | Q9: Pending | R9: 0 | S9: Active
A10: Hans MÃ¼ller | B10: hans_muller | C10: Business | D10: Germany | E10: Berlin | F10: 52 | G10: Male | H10: hans.muller@company.de | I10: =49-170-1234567 -> -1234688 | J10: 43072 | K10: 45299 | L10: 124500.9 | M10: 75000.4 | N10: 665 | O10: 150000 | P10: High | Q10: Verified | R10: 0 | S10: Active
A11: Fatima Al Mansouri | B11: fatima_alm | C11: Joint | D11: UAE | E11: Dubai | F11: 36 | G11: Female | H11: fatima.mansouri@email.ae | I11: =971-50-345-6789 -> -6213 | J11: 44311 | K11: 45303 | L11: 78900.25 | M11: 32000.75 | N11: 730 | O11: 110000 | P11: Medium | Q11: Verified | R11: 0 | S11: Active
A12: James Wilson-Smith | B12: james_wilson | C12: Student | D12: Canada | E12: Toronto | F12: 21 | G12: Male | H12: james.wilson@edu.ca | I12: =1-416-555-189 -> -1159 | J12: 45179 | K12: 45304 | L12: 3200.5 | M12: 12500.8 | N12: 625 | O12: 22000 | P12: High | Q12: Pending | R12: 0 | S12: Active
A13: Yuki Nakamura | B13: yuki_nakamura | C13: Premium | D13: Japan | E13: Osaka | F13: 48 | G13: Female | H13: yuki.nakamura@mail.jp | I13: =81-80-9876-5432 -> -15307 | J13: 43847 | K13: 45301 | L13: 95600.4 | M13: 28000.6 | N13: 775 | O13: 125000 | P13: Low | Q13: Verified | R13: 0 | S13: Active
A14: Rajesh Kumar Patel | B14: rajesh_patel | C14: Savings | D14: India | E14: Delhi | F14: 33 | G14: Male | H14: rajesh.patel@email.in | I14: =91-989-876-5432 -> -7206 | J14: 44530 | K14: 45302 | L14: 42300.8 | M14: 19500.25 | N14: 690 | O14: 78000 | P14: Medium | Q14: Verified | R14: 0 | S14: Active
A15: Sarah Johnson-Williams | B15: sarah_jw | C15: Current | D15: UK | E15: Manchester | F15: 29 | G15: Female | H15: sarah.jw@email.co.uk | I15: =44-16-1837-4650 -> -6459 | J15: 44642 | K15: 45305 | L15: 15800.9 | M15: 8200.75 | N15: 745 | O15: 52000 | P15: Low | Q15: Verified | R15: 0 | S15: Active
A16: Mohammed Hassan | B16: mohammed_h | C16: Business | D16: UAE | E16: Abu Dhabi | F16: 44 | G16: Male | H16: mohammed.hassan@business.ae | I16: =971-56-789-123 -> 3 | J16: 43300 | K16: 45300 | L16: 187600.3 | M16: 92000.8 | N16: 655 | O16: 180000 | P16: High | Q16: Verified | R16: 0 | S16: Active
A17: Luciana Costa | B17: lucia_costa | C17: Digital-Only | D17: Brazil | E17: Rio de Janeiro | F17: 27 | G17: Female | H17: luciana.costa@mail.br | I17: =55-21-99876-5432 -> -105274 | J17: 44941 | K17: 45306 | L17: 7200.4 | M17: 4800.9 | N17: 720 | O17: 41000 | P17: Low | Q17: Verified | R17: 0 | S17: Active
A18: Kenji Sato | B18: kenji_sato | C18: Premium | D18: Japan | E18: Kyoto | F18: 55 | G18: Male | H18: kenji.sato@company.jp | I18: =81-75-234-5678 -> -5906 | J18: 42641 | K18: 45299 | L18: 203400.75 | M18: 45000.25 | N18: 805 | O18: 220000 | P18: Low | Q18: Verified | R18: 0 | S18: Active
A19: Adebola Okafor | B19: adebola_o | C19: Savings | D19: Nigeria | E19: Abuja | F19: 38 | G19: Male | H19: adebola.okafor@email.ng | I19: =234-802-345-6789 -> -7702 | J19: 43996 | K19: 45303 | L19: 28900.6 | M19: 13400.8 | N19: 675 | O19: 72000 | P19: Medium | Q19: Verified | R19: 0 | S19: Active
A20: Emma-Rose Gallagher | B20: emma_rose | C20: Student | D20: US | E20: Los Angeles | F20: 20 | G20: Female | H20: emma.gallagher@edu.com | I20: =1-213-555-176 -> -943 | J20: 45143 | K20: 45304 | L20: 1850.25 | M20: 9500.4 | N20: 610 | O20: 18000 | P20: High | Q20: Pending | R20: 0 | S20: Active
A21: Chen Wei | B21: chen_wei88 | C21: Current | D21: China | E21: Beijing | F21: 32 | G21: Male | H21: chen.wei@mail.cn | I21: =86-139-8765-4321 -> -13139 | J21: 44255 | K21: 45301 | L21: 24300.7 | M21: 11200.5 | N21: 760 | O21: 67000 | P21: Low | Q21: Verified | R21: 0 | S21: Active
A22: Sophie Schmidt | B22: sophie_schmidt | C22: Savings | D22: Germany | E22: Hamburg | F22: 41 | G22: Female | H22: sophie.schmidt@email.de | I22: =49-171-9876543 -> -9876665 | J22: 43573 | K22: 45302 | L22: 38700.25 | M22: 14500.6 | N22: 735 | O22: 89000 | P22: Low | Q22: Verified | R22: 0 | S22: Active
A23: David Chen-Li | B23: david_chenli | C23: Joint | D23: Canada | E23: Vancouver | F23: 37 | G23: Male | H23: david.chenli@email.ca | I23: =1-604-555-167 -> -1325 | J23: 44126 | K23: 45300 | L23: 54200.8 | M23: 22800.75 | N23: 710 | O23: 105000 | P23: Medium | Q23: Verified | R23: 0 | S23: Active
A24: Priya Sharma | B24: priya_sharma | C24: Digital-Only | D24: India | E24: Bangalore | F24: 26 | G24: Female | H24: priya.sharma@mail.in | I24: =91-876-543-2109 -> -3437 | J24: 44995 | K24: 45305 | L24: 8900.4 | M24: 5200.25 | N24: 690 | O24: 35000 | P24: Medium | Q24: Pending | R24: 0 | S24: Active
A25: Ahmed Abdullah | B25: ahmed_abdullah | C25: Business | D25: UAE | E25: Sharjah | F25: 49 | G25: Male | H25: ahmed.abdullah@company.ae | I25: =971-55-678-9012 -> -8774 | J25: 43054 | K25: 45299 | L25: 156800.6 | M25: 78000.4 | N25: 645 | O25: 165000 | P25: High | Q25: Verified | R25: 0 | S25: Active
A26: Isabella Rossi | B26: isabella_r | C26: Current | D26: Brazil | E26: SÃ£o Paulo | F26: 30 | G26: Female | H26: isabella.rossi@email.com.br | I26: =55-11-98765-4321 -> -103042 | J26: 44535 | K26: 45303 | L26: 19200.75 | M26: 8600.9 | N26: 755 | O26: 58000 | P26: Low | Q26: Verified | R26: 0 | S26: Active
A27: Takashi Yamamoto | B27: takashi_y | C27: Premium | D27: Japan | E27: Tokyo | F27: 53 | G27: Male | H27: takashi.yamamoto@mail.jp | I27: =81-70-3456-7890 -> -11335 | J27: 43159 | K27: 45301 | L27: 178900.25 | M27: 52000.8 | N27: 790 | O27: 195000 | P27: Low | Q27: Verified | R27: 0 | S27: Active
A28: Chukwuma Eze | B28: chukwuma_e | C28: Savings | D28: Nigeria | E28: Lagos | F28: 43 | G28: Male | H28: chukwuma.eze@email.ng | I28: =234-815-678-9012 -> -10271 | J28: 43660 | K28: 45302 | L28: 45600.9 | M28: 21300.6 | N28: 665 | O28: 95000 | P28: Medium | Q28: Verified | R28: 0 | S28: Active
A29: Benjamin Taylor | B29: ben_taylor | C29: Student | D29: UK | E29: London | F29: 19 | G29: Male | H29: ben.taylor@edu.ac.uk | I29: =44-79-8765-4321 -> -13121 | J29: 45207 | K29: 45304 | L29: 2250.8 | M29: 11200.75 | N29: 595 | O29: 16000 | P29: High | Q29: Pending | R29: 0 | S29: Active
A30: Mei Lin | B30: mei_lin92 | C30: Digital-Only | D30: China | E30: Guangzhou | F30: 29 | G30: Female | H30: mei.lin@mail.cn | I30: =86-137-1234-5678 -> -6963 | J30: 44788 | K30: 45305 | L30: 11200.3 | M30: 4800.4 | N30: 775 | O30: 43000 | P30: Low | Q30: Verified | R30: 0 | S30: Active
A31: Klaus Weber | B31: klaus_weber | C31: Business | D31: Germany | E31: Munich | F31: 47 | G31: Male | H31: klaus.weber@firm.de | I31: =49-172-3456789 -> -3456912 | J31: 43363 | K31: 45300 | L31: 134200.4 | M31: 65000.25 | N31: 670 | O31: 140000 | P31: High | Q31: Verified | R31: 0 | S31: Active
A32: Olivia Martin | B32: olivia_martin | C32: Joint | D32: Canada | E32: Montreal | F32: 34 | G32: Female | H32: olivia.martin@email.ca | I32: =1-514-555-154 -> -1222 | J32: 44168 | K32: 45303 | L32: 62300.6 | M32: 24500.8 | N32: 725 | O32: 98000 | P32: Medium | Q32: Verified | R32: 0 | S32: Active
A33: Arjun Desai | B33: arjun_desai | C33: Savings | D33: India | E33: Chennai | F33: 40 | G33: Male | H33: arjun.desai@email.in | I33: =91-765-432-1098 -> -2204 | J33: 43610 | K33: 45301 | L33: 51800.75 | M33: 23800.4 | N33: 700 | O33: 110000 | P33: Medium | Q33: Verified | R33: 0 | S33: Active
A34: Layla Al Qasimi | B34: layla_alq | C34: Current | D34: UAE | E34: Dubai | F34: 27 | G34: Female | H34: layla.alqasimi@email.ae | I34: =971-52-456-7890 -> -7427 | J34: 44668 | K34: 45305 | L34: 14300.2 | M34: 6200.75 | N34: 740 | O34: 49000 | P34: Low | Q34: Verified | R34: 0 | S34: Active
A35: Ricardo Oliveira | B35: ricardo_o | C35: Premium | D35: Brazil | E35: Rio de Janeiro | F35: 51 | G35: Male | H35: ricardo.oliveira@email.com.br | I35: =55-21-97654-3210 -> -100830 | J35: 42898 | K35: 45299 | L35: 198700.8 | M35: 58000.6 | N35: 780 | O35: 210000 | P35: Low | Q35: Verified | R35: 0 | S35: Active
A36: Yumi Kobayashi | B36: yumi_k | C36: Digital-Only | D36: Japan | E36: Osaka | F36: 25 | G36: Female | H36: yumi.kobayashi@mail.jp | I36: =81-90-6789-123 -> -6921 | J36: 45021 | K36: 45306 | L36: 6800.9 | M36: 3800.25 | N36: 720 | O36: 32000 | P36: Medium | Q36: Pending | R36: 0 | S36: Active
A37: Femi Balogun | B37: femi_balogun | C37: Business | D37: Nigeria | E37: Port Harcourt | F37: 46 | G37: Male | H37: femi.balogun@company.ng | I37: =234-706-789-123 -> -1384 | J37: 43342 | K37: 45300 | L37: 123800.25 | M37: 59000.75 | N37: 635 | O37: 135000 | P37: High | Q37: Verified | R37: 0 | S37: Active
A38: Charlotte Dubois | B38: charlotte_d | C38: Joint | D38: France | E38: Paris | F38: 33 | G38: Female | H38: charlotte.dubois@email.fr | I38: =33-6-1234-5678 -> -6885 | J38: 44210 | K38: 45302 | L38: 47800.4 | M38: 19500.9 | N38: 750 | O38: 92000 | P38: Low | Q38: Verified | R38: 0 | S38: Active
A39: Michael Brown | B39: mike_brown | C39: Savings | D39: US | E39: Houston | F39: 39 | G39: Male | H39: mike.brown@email.com | I39: =1-832-555-134 -> -1520 | J39: 43791 | K39: 45301 | L39: 34200.6 | M39: 12800.25 | N39: 710 | O39: 78000 | P39: Medium | Q39: Verified | R39: 0 | S39: Active
A40: Ananya Reddy | B40: ananya_reddy | C40: Student | D40: India | E40: Mumbai | F40: 22 | G40: Female | H40: ananya.reddy@edu.in | I40: =91-854-321-987 -> -2071 | J40: 45126 | K40: 45304 | L40: 1950.4 | M40: 8800.6 | N40: 605 | O40: 20000 | P40: High | Q40: Pending | R40: 0 | S40: Active
A41: Liam O'Connor | B41: liam_oconnor | C41: Current | D41: Ireland | E41: Dublin | F41: 28 | G41: Male | H41: liam.oconnor@email.ie | I41: =353-85-123-4567 -> -4422 | J41: 44620 | K41: 45305 | L41: 12800.75 | M41: 5400.8 | N41: 730 | O41: 45000 | P41: Low | Q41: Verified | R41: 0 | S41: Active
A42: Xiao Wang | B42: xiao_wang | C42: Business | D42: China | E42: Shenzhen | F42: 44 | G42: Male | H42: xiao.wang@company.cn | I42: =86-136-8765-4321 -> -13136 | J42: 43205 | K42: 45300 | L42: 167400.6 | M42: 82000.4 | N42: 685 | O42: 175000 | P42: High | Q42: Verified | R42: 0 | S42: Active
A43: Elena Petrova | B43: elena_p | C43: Savings | D43: Russia | E43: Moscow | F43: 36 | G43: Female | H43: elena.petrova@email.ru | I43: =7-915-123-45-67 -> -1143 | J43: 44020 | K43: 45303 | L43: 29800.8 | M43: 13400.25 | N43: 695 | O43: 68000 | P43: Medium | Q43: Verified | R43: 0 | S43: Active
A44: Juan Carlos Martinez | B44: juan_c_m | C44: Digital-Only | D44: Mexico | E44: Mexico City | F44: 31 | G44: Male | H44: juan.martinez@mail.mx | I44: =52-55-1234-5678 -> -6915 | J44: 44816 | K44: 45305 | L44: 10200.5 | M44: 4500.75 | N44: 715 | O44: 47000 | P44: Low | Q44: Verified | R44: 0 | S44: Active
A45: Sofia Garcia | B45: sofia_g | C45: Joint | D45: Spain | E45: Madrid | F45: 38 | G45: Female | H45: sofia.garcia@email.es | I45: =34-612-345-678 -> -1601 | J45: 43915 | K45: 45302 | L45: 56700.3 | M45: 22300.6 | N45: 740 | O45: 105000 | P45: Medium | Q45: Verified | R45: 0 | S45: Active
A46: Kwame Nkrumah | B46: kwame_n | C46: Savings | D46: Ghana | E46: Accra | F46: 42 | G46: Male | H46: kwame.nkrumah@email.gh | I46: =233-24-456-7890 -> -8137 | J46: 43634 | K46: 45301 | L46: 38700.75 | M46: 16800.4 | N46: 660 | O46: 82000 | P46: Medium | Q46: Verified | R46: 0 | S46: Active
A47: Hiroshi Tanaka | B47: hiroshi_t | C47: Premium | D47: Japan | E47: Nagoya | F47: 57 | G47: Male | H47: hiroshi.tanaka@mail.jp | I47: =81-80-2345-6789 -> -9133 | J47: 42714 | K47: 45299 | L47: 234500.4 | M47: 62000.8 | N47: 815 | O47: 240000 | P47: Low | Q47: Verified | R47: 0 | S47: Active
A48: Aisha Mohammed | B48: aisha_m | C48: Current | D48: Kenya | E48: Nairobi | F48: 26 | G48: Female | H48: aisha.mohammed@email.ke | I48: =254-712-345-678 -> -1481 | J48: 44956 | K48: 45306 | L48: 8900.25 | M48: 3800.9 | N48: 680 | O48: 36000 | P48: Medium | Q48: Pending | R48: 0 | S48: Active
A49: Daniel Kim | B49: daniel_kim | C49: Business | D49: South Korea | E49: Seoul | F49: 48 | G49: Male | H49: daniel.kim@company.kr | I49: =82-10-1234-5678 -> -6840 | J49: 43013 | K49: 45300 | L49: 189600.75 | M49: 87000.25 | N49: 700 | O49: 190000 | P49: High | Q49: Verified | R49: 0 | S49: Active
A50: Lisa Schmidt | B50: lisa_schmidt | C50: Student | D50: Germany | E50: Berlin | F50: 20 | G50: Female | H50: lisa.schmidt@edu.de | I50: =49-173-4567890 -> -4568014 | J50: 45160 | K50: 45304 | L50: 2450.6 | M50: 10500.4 | N50: 615 | O50: 17000 | P50: High | Q50: Pending | R50: 0 | S50: Active
A51: Marco Rossi | B51: marco_r | C51: Joint | D51: Italy | E51: Rome | F51: 35 | G51: Male | H51: marco.rossi@email.it | I51: =39-345-678-9012 -> -9996 | J51: 44330 | K51: 45303 | L51: 51200.9 | M51: 21800.75 | N51: 730 | O51: 96000 | P51: Medium | Q51: Verified | R51: 0 | S51: Active
A52: Jennifer Lopez | B52: jen_lopez | C52: Digital-Only | D52: US | E52: Phoenix | F52: 29 | G52: Female | H52: jen.lopez@mail.com | I52: =1-602-555-178 -> -1334 | J52: 44872 | K52: 45305 | L52: 11500.8 | M52: 5200.3 | N52: 760 | O52: 52000 | P52: Low | Q52: Verified | R52: 0 | S52: Active
A53: Rahul Mehta | B53: rahul_mehta | C53: Savings | D53: India | E53: Kolkata | F53: 45 | G53: Male | H53: rahul.mehta@email.in | I53: =91-743-210-9876 -> -10738 | J53: 43120 | K53: 45300 | L53: 67800.4 | M53: 31200.6 | N53: 675 | O53: 125000 | P53: Medium | Q53: Verified | R53: 0 | S53: Active
A54: Fatoumata Diallo | B54: fatou_d | C54: Current | D54: Senegal | E54: Dakar | F54: 32 | G54: Female | H54: fatou.diallo@email.sn | I54: =221-77-123-45-67 -> -91 | J54: 44417 | K54: 45302 | L54: 23400.75 | M54: 9800.25 | N54: 710 | O54: 61000 | P54: Low | Q54: Verified | R54: 0 | S54: Active
A55: Alexander Petrov | B55: alex_p | C55: Business | D55: Russia | E55: St. Petersburg | F55: 50 | G55: Male | H55: alex.petrov@company.ru | I55: =7-921-987-65-43 -> -2009 | J55: 42806 | K55: 45299 | L55: 156300.2 | M55: 74000.8 | N55: 655 | O55: 160000 | P55: High | Q55: Verified | R55: 0 | S55: Active
A56: Ying Chen | B56: ying_chen | C56: Premium | D56: China | E56: Beijing | F56: 54 | G56: Female | H56: ying.chen@mail.cn | I56: =86-139-2345-6789 -> -9187 | J56: 42607 | K56: 45301 | L56: 287400.6 | M56: 75000.4 | N56: 825 | O56: 260000 | P56: Low | Q56: Verified | R56: 0 | S56: Active
A57: Samuel Johnson | B57: sam_johnson | C57: Joint | D57: UK | E57: Birmingham | F57: 41 | G57: Male | H57: sam.johnson@email.co.uk | I57: =44-78-9123-4567 -> -13724 | J57: 43738 | K57: 45303 | L57: 73400.25 | M57: 28900.75 | N57: 720 | O57: 135000 | P57: Medium | Q57: Verified | R57: 0 | S57: Active
A58: Ngozi Okonkwo | B58: ngozio | C58: Business | D58: Nigeria | E58: Lagos | F58: 47 | G58: Female | H58: ngozi.okonkwo@company.ng | I58: =234-803-456-7890 -> -8915 | J58: 43237 | K58: 45300 | L58: 142800.9 | M58: 68000.6 | N58: 640 | O58: 145000 | P58: High | Q58: Verified | R58: 0 | S58: Active
A59: Pierre Moreau | B59: pierre_m | C59: Savings | D59: France | E59: Lyon | F59: 37 | G59: Male | H59: pierre.moreau@email.fr | I59: =33-7-8765-4321 -> -13060 | J59: 43932 | K59: 45302 | L59: 42300.8 | M59: 15600.4 | N59: 745 | O59: 88000 | P59: Low | Q59: Verified | R59: 0 | S59: Active
A60: Amina Hassan | B60: amina_h | C60: Digital-Only | D60: Egypt | E60: Cairo | F60: 24 | G60: Female | H60: amina.hassan@mail.eg | I60: =20-100-123-4567 -> -4770 | J60: 44985 | K60: 45306 | L60: 7400.6 | M60: 4200.75 | N60: 695 | O60: 31000 | P60: Medium | Q60: Pending | R60: 0 | S60: Active
A61: Thomas Anderson | B61: t_anderson | C61: Current | D61: US | E61: Seattle | F61: 33 | G61: Male | H61: thomas.anderson@email.com | I61: =1-206-555-162 -> -922 | J61: 44396 | K61: 45303 | L61: 18700.4 | M61: 7200.9 | N61: 770 | O61: 63000 | P61: Low | Q61: Verified | R61: 0 | S61: Active
A62: Siti Rahman | B62: siti_rahman | C62: Joint | D62: Malaysia | E62: Kuala Lumpur | F62: 39 | G62: Female | H62: siti.rahman@email.my | I62: =60-12-345-6789 -> -7086 | J62: 44109 | K62: 45301 | L62: 58900.75 | M62: 23400.25 | N62: 705 | O62: 112000 | P62: Medium | Q62: Verified | R62: 0 | S62: Active
A63: Diego Ramirez | B63: diego_r | C63: Savings | D63: Colombia | E63: BogotÃ¡ | F63: 43 | G63: Male | H63: diego.ramirez@email.co | I63: =57-300-123-4567 -> -4933 | J63: 43510 | K63: 45300 | L63: 45600.3 | M63: 19800.8 | N63: 680 | O63: 97000 | P63: Medium | Q63: Verified | R63: 0 | S63: Active
A64: Hana Kim | B64: hana_k | C64: Premium | D64: South Korea | E64: Busan | F64: 52 | G64: Female | H64: hana.kim@mail.kr | I64: =82-10-9876-5432 -> -15236 | J64: 43047 | K64: 45299 | L64: 213800.4 | M64: 58000.75 | N64: 795 | O64: 225000 | P64: Low | Q64: Verified | R64: 0 | S64: Active
A65: James O'Malley | B65: james_omalley | C65: Student | D65: Ireland | E65: Cork | F65: 21 | G65: Male | H65: james.omalley@edu.ie | I65: =353-86-234-5678 -> -5645 | J65: 45184 | K65: 45304 | L65: 2100.25 | M65: 9800.6 | N65: 600 | O65: 19000 | P65: High | Q65: Pending | R65: 0 | S65: Active
A66: Ling Wong | B66: ling_wong | C66: Business | D66: Singapore | E66: Singapore | F66: 49 | G66: Male | H66: ling.wong@company.sg | I66: =65-9123-4567 -> -13625 | J66: 43303 | K66: 45300 | L66: 178900.75 | M66: 85000.4 | N66: 690 | O66: 185000 | P66: High | Q66: Verified | R66: 0 | S66: Active
A67: Maria Gonzalez | B67: maria_g | C67: Current | D67: Argentina | E67: Buenos Aires | F67: 30 | G67: Female | H67: maria.gonzalez@email.ar | I67: =54-9-11-2345-6789 -> -9100 | J67: 44586 | K67: 45305 | L67: 12300.9 | M67: 5400.25 | N67: 740 | O67: 55000 | P67: Low | Q67: Verified | R67: 0 | S67: Active
A68: Ahmed Khan | B68: ahmed_k | C68: Savings | D68: Pakistan | E68: Karachi | F68: 44 | G68: Male | H68: ahmed.khan@email.pk | I68: =92-300-1234567 -> -1234775 | J68: 43558 | K68: 45301 | L68: 51200.6 | M68: 23500.75 | N68: 665 | O68: 108000 | P68: Medium | Q68: Verified | R68: 0 | S68: Active
A69: Yuki Sato | B69: yuki_s | C69: Digital-Only | D69: Japan | E69: Tokyo | F69: 27 | G69: Female | H69: yuki.sato@mail.jp | I69: =81-90-4567-8901 -> -13477 | J69: 45003 | K69: 45305 | L69: 8300.4 | M69: 4600.8 | N69: 710 | O69: 34000 | P69: Medium | Q69: Pending | R69: 0 | S69: Active
A70: Robert Wilson | B70: rob_wilson | C70: Joint | D70: Australia | E70: Sydney | F70: 38 | G70: Male | H70: rob.wilson@email.au | I70: =61-412-345-678 -> -1374 | J70: 44055 | K70: 45302 | L70: 67800.25 | M70: 25600.4 | N70: 730 | O70: 121000 | P70: Medium | Q70: Verified | R70: 0 | S70: Active
A71: Fatima Zahra | B71: fatima_z | C71: Current | D71: Morocco | E71: Casablanca | F71: 31 | G71: Female | H71: fatima.zahra@email.ma | I71: =212-612-345-678 -> -1423 | J71: 44538 | K71: 45303 | L71: 15600.8 | M71: 6800.9 | N71: 725 | O71: 59000 | P71: Low | Q71: Verified | R71: 0 | S71: Active
A72: Miguel Santos | B72: miguel_s | C72: Business | D72: Brazil | E72: SÃ£o Paulo | F72: 53 | G72: Male | H72: miguel.santos@company.br | I72: =55-11-93456-7890 -> -101302 | J72: 42983 | K72: 45299 | L72: 198500.6 | M72: 92000.25 | N72: 675 | O72: 205000 | P72: High | Q72: Verified | R72: 0 | S72: Active
A73: Sarah Chen | B73: sarah_chen | C73: Premium | D73: Canada | E73: Toronto | F73: 46 | G73: Female | H73: sarah.chen@email.ca | I73: =1-647-555-192 -> -1393 | J73: 43454 | K73: 45301 | L73: 187600.4 | M73: 52000.8 | N73: 810 | O73: 195000 | P73: Low | Q73: Verified | R73: 0 | S73: Active
A74: Ravi Shankar | B74: ravi_shankar | C74: Savings | D74: India | E74: Delhi | F74: 41 | G74: Male | H74: ravi.shankar@email.in | I74: =91-832-109-8765 -> -9615 | J74: 43753 | K74: 45302 | L74: 62300.75 | M74: 28500.6 | N74: 690 | O74: 132000 | P74: Medium | Q74: Verified | R74: 0 | S74: Active
A75: Emma van der Berg | B75: emma_vdb | C75: Current | D75: Netherlands | E75: Amsterdam | F75: 29 | G75: Female | H75: emma.vanderberg@email.nl | I75: =31-6-1234-5678 -> -6887 | J75: 44703 | K75: 45305 | L75: 13400.2 | M75: 5800.75 | N75: 755 | O75: 51000 | P75: Low | Q75: Verified | R75: 0 | S75: Active
A76: Omar Farooq | B76: omar_f | C76: Business | D76: Bangladesh | E76: Dhaka | F76: 48 | G76: Male | H76: omar.farooq@company.bd | I76: =880-1712-345678 -> -346510 | J76: 43187 | K76: 45300 | L76: 123700.8 | M76: 59000.4 | N76: 645 | O76: 135000 | P76: High | Q76: Verified | R76: 0 | S76: Active
A77: Chloe Dubois | B77: chloe_d | C77: Student | D77: France | E77: Paris | F77: 20 | G77: Female | H77: chloe.dubois@edu.fr | I77: =33-7-2345-6789 -> -9108 | J77: 45209 | K77: 45304 | L77: 1950.8 | M77: 9200.25 | N77: 610 | O77: 17000 | P77: High | Q77: Pending | R77: 0 | S77: Active
A78: Kenji Watanabe | B78: kenji_w | C78: Premium | D78: Japan | E78: Osaka | F78: 58 | G78: Male | H78: kenji.watanabe@mail.jp | I78: =81-80-5678-9012 -> -14689 | J78: 42504 | K78: 45299 | L78: 256300.75 | M78: 68000.9 | N78: 820 | O78: 270000 | P78: Low | Q78: Verified | R78: 0 | S78: Active
A79: Adeyemi Adebayo | B79: adeyemi_a | C79: Savings | D79: Nigeria | E79: Ibadan | F79: 39 | G79: Male | H79: adeyemi.adebayo@email.ng | I79: =234-807-890-1234 -> -2697 | J79: 43890 | K79: 45301 | L79: 34500.6 | M79: 15200.75 | N79: 670 | O79: 78000 | P79: Medium | Q79: Verified | R79: 0 | S79: Active
A80: Isabelle Laurent | B80: isabelle_l | C80: Joint | D80: Switzerland | E80: Zurich | F80: 36 | G80: Female | H80: isabelle.laurent@email.ch | I80: =41-76-123-45-67 -> -270 | J80: 44293 | K80: 45303 | L80: 78900.4 | M80: 31200.8 | N80: 760 | O80: 142000 | P80: Medium | Q80: Verified | R80: 0 | S80: Active
A81: David Park | B81: david_park | C81: Digital-Only | D81: South Korea | E81: Seoul | F81: 26 | G81: Male | H81: david.park@mail.kr | I81: =82-10-2345-6789 -> -9062 | J81: 45089 | K81: 45305 | L81: 9200.75 | M81: 5100.4 | N81: 730 | O81: 38000 | P81: Low | Q81: Verified | R81: 0 | S81: Active
A82: Samantha Jones | B82: sam_jones | C82: Current | D82: UK | E82: London | F82: 32 | G82: Female | H82: samantha.jones@email.co.uk | I82: =44-79-8234-5678 -> -13947 | J82: 44530 | K82: 45302 | L82: 17800.9 | M82: 7600.25 | N82: 740 | O82: 67000 | P82: Low | Q82: Verified | R82: 0 | S82: Active
A83: Mohammad Ali | B83: m_ali | C83: Business | D83: Saudi Arabia | E83: Riyadh | F83: 51 | G83: Male | H83: mohammad.ali@company.sa | I83: =966-50-123-4567 -> -3774 | J83: 42934 | K83: 45299 | L83: 234800.2 | M83: 105000.6 | N83: 660 | O83: 240000 | P83: High | Q83: Verified | R83: 0 | S83: Active
A84: Lina Nguyen | B84: lina_nguyen | C84: Savings | D84: Vietnam | E84: Hanoi | F84: 35 | G84: Female | H84: lina.nguyen@email.vn | I84: =84-912-345-678 -> -1851 | J84: 44099 | K84: 45301 | L84: 29800.4 | M84: 12300.75 | N84: 700 | O84: 71000 | P84: Medium | Q84: Verified | R84: 0 | S84: Active
A85: Brian Taylor | B85: brian_t | C85: Joint | D85: US | E85: San Francisco | F85: 42 | G85: Male | H85: brian.taylor@email.com | I85: =1-415-555-183 -> -1152 | J85: 43807 | K85: 45303 | L85: 85600.75 | M85: 34200.4 | N85: 715 | O85: 148000 | P85: Medium | Q85: Verified | R85: 0 | S85: Active
A86: Zara Khan | B86: zara_k | C86: Student | D86: Pakistan | E86: Lahore | F86: 23 | G86: Female | H86: zara.khan@edu.pk | I86: =92-322-9876543 -> -9876773 | J86: 45143 | K86: 45304 | L86: 1650.2 | M86: 7500.8 | N86: 615 | O86: 21000 | P86: High | Q86: Pending | R86: 0 | S86: Active
A87: Giuseppe Romano | B87: giuseppe_r | C87: Premium | D87: Italy | E87: Milan | F87: 55 | G87: Male | H87: giuseppe.romano@mail.it | I87: =39-347-123-4567 -> -4998 | J87: 42665 | K87: 45299 | L87: 298700.4 | M87: 72000.25 | N87: 835 | O87: 280000 | P87: Low | Q87: Verified | R87: 0 | S87: Active
A88: Nadia Petrova | B88: nadia_p | C88: Current | D88: Ukraine | E88: Kyiv | F88: 33 | G88: Female | H88: nadia.petrova@email.ua | I88: =380-67-123-4567 -> -4377 | J88: 44269 | K88: 45302 | L88: 14200.6 | M88: 6100.9 | N88: 725 | O88: 57000 | P88: Low | Q88: Verified | R88: 0 | S88: Active
A89: Kevin O'Brien | B89: kevin_obrien | C89: Business | D89: Ireland | E89: Dublin | F89: 49 | G89: Male | H89: kevin.obrien@company.ie | I89: =353-87-234-5678 -> -5646 | J89: 43281 | K89: 45300 | L89: 167800.75 | M89: 78000.6 | N89: 675 | O89: 175000 | P89: High | Q89: Verified | R89: 0 | S89: Active
A90: Yuna Kim | B90: yuna_kim | C90: Digital-Only | D90: South Korea | E90: Seoul | F90: 28 | G90: Female | H90: yuna.kim@mail.kr | I90: =82-10-3456-7890 -> -11274 | J90: 44898 | K90: 45305 | L90: 10800.25 | M90: 5900.4 | N90: 745 | O90: 46000 | P90: Low | Q90: Verified | R90: 0 | S90: Active
A91: Ahmed Mohamed | B91: ahmed_m | C91: Savings | D91: Egypt | E91: Alexandria | F91: 40 | G91: Male | H91: ahmed.mohamed@email.eg | I91: =20-122-345-6789 -> -7236 | J91: 43847 | K91: 45301 | L91: 43200.8 | M91: 18700.25 | N91: 680 | O91: 93000 | P91: Medium | Q91: Verified | R91: 0 | S91: Active
A92: Sophia Williams | B92: sophia_w | C92: Joint | D92: US | E92: Boston | F92: 37 | G92: Female | H92: sophia.williams@email.com | I92: =1-617-555-156 -> -1327 | J92: 44034 | K92: 45302 | L92: 72300.6 | M92: 28900.75 | N92: 750 | O92: 128000 | P92: Medium | Q92: Verified | R92: 0 | S92: Active
A93: Raj Malhotra | B93: raj_m | C93: Business | D93: India | E93: Mumbai | F93: 52 | G93: Male | H93: raj.malhotra@company.in | I93: =91-876-543-2109 -> -3437 | J93: 42837 | K93: 45299 | L93: 198400.25 | M93: 89000.4 | N93: 655 | O93: 210000 | P93: High | Q93: Verified | R93: 0 | S93: Active
A94: Marta Silva | B94: marta_s | C94: Current | D94: Portugal | E94: Lisbon | F94: 31 | G94: Female | H94: marta.silva@email.pt | I94: =351-912-345-678 -> -1584 | J94: 44444 | K94: 45303 | L94: 12300.4 | M94: 5200.8 | N94: 735 | O94: 54000 | P94: Low | Q94: Verified | R94: 0 | S94: Active
A95: Takeshi Nakamura | B95: takeshi_n | C95: Premium | D95: Japan | E95: Tokyo | F95: 59 | G95: Male | H95: takeshi.nakamura@mail.jp | I95: =81-90-6789-123 -> -6921 | J95: 42454 | K95: 45299 | L95: 312500.6 | M95: 85000.75 | N95: 845 | O95: 295000 | P95: Low | Q95: Verified | R95: 0 | S95: Active
A96: Babatunde Adeyemi | B96: babatunde_a | C96: Savings | D96: Nigeria | E96: Lagos | F96: 45 | G96: Male | H96: babatunde.adeyemi@email.ng | I96: =234-809-12-3456 -> -4043 | J96: 43696 | K96: 45301 | L96: 56700.3 | M96: 24500.4 | N96: 665 | O96: 118000 | P96: Medium | Q96: Verified | R96: 0 | S96: Active
A97: Elena Costa | B97: elena_c | C97: Joint | D97: Brazil | E97: SÃ£o Paulo | F97: 34 | G97: Female | H97: elena.costa@email.com.br | I97: =55-11-94567-8901 -> -103424 | J97: 44255 | K97: 45303 | L97: 67800.75 | M97: 25600.9 | N97: 740 | O97: 124000 | P97: Medium | Q97: Verified | R97: 0 | S97: Active
A98: Mark Thompson | B98: mark_t | C98: Digital-Only | D98: US | E98: Chicago | F98: 27 | G98: Male | H98: mark.thompson@mail.com | I98: =1-773-555-198 -> -1525 | J98: 45031 | K98: 45305 | L98: 8900.6 | M98: 4800.25 | N98: 710 | O98: 43000 | P98: Medium | Q98: Pending | R98: 0 | S98: Active
A99: Anh Tran | B99: anh_tran | C99: Business | D99: Vietnam | E99: Ho Chi Minh City | F99: 47 | G99: Male | H99: anh.tran@company.vn | I99: =84-903-456-789 -> -2064 | J99: 43424 | K99: 45300 | L99: 134600.4 | M99: 62000.75 | N99: 670 | O99: 145000 | P99: High | Q99: Verified | R99: 0 | S99: Active
A100: Laura MÃ¼ller | B100: laura_m | C100: Student | D100: Germany | E100: Hamburg | F100: 22 | G100: Female | H100: laura.muller@edu.de | I100: =49-174-5678901 -> -5679026 | J100: 45119 | K100: 45304 | L100: 2280.4 | M100: 10800.6 | N100: 605 | O100: 18000 | P100: High | Q100: Pending | R100: 0 | S100: Active
...

Sheet Data Table
A1: Full Name | B1: Username | C1: Account Type | D1: Country | E1: City | F1: Age | G1: Gender | H1: Email | I1: Phone Number | J1: Account Creation Date | K1: Last Active Date | L1: Balance (USD) | M1: Debt (USD) | N1: Credit Score | O1: Income Level (USD Annual) | P1: Risk Category | Q1: KYC Status | R1: Fraud Flag | S1: Account Status | T1: Debt Ratio | U1: Days Inactive | V1: Credit Score Band | W1: Age Group | X1: Income categories
A2: Carlos M. Rivera Jr. | B2: carlos_rivera23 | C2: Premium | D2: US | E2: New York | F2: 42 | G2: Male | H2: carlos.rivera23@email.com | I2: +1-718-555-0199 | J2: 43539 | K2: 45303 | L2: 45250.75 | M2: 12500.5 | N2: 745 | O2: 85000 | P2: Medium | Q2: Verified | R2: 0 | S2: Active | T2: =IFERROR(M2/O2,"") -> 0.14706471 | U2: =MAX($K$2:$K$1599)-K2 -> 3 | V2: =IF(N2<670,"FAIR", IF(N2<750,"GOOD",IF(N2<800,"VERY GOOD","EXCEPTIONAL"))) -> GOOD | W2: =IF(F2<25,"18-24",IF(F2<35,"25-34",IF(F2<45,"35-44",IF(F2<55,"45-54","55+")))) -> 35-44 | X2: =IF(O2<=_xlfn.QUARTILE.INC($O$2:$O$1599,1),"Low",IF(O2<=_xlfn.QUARTILE.INC($O$2:$O$1599,2),"Lower-Middle",IF(O2<=_xlfn.QUARTILE.INC($O$2:$O$1599,3),"Upper-Middle","High"))) -> Lower-Middle
A3: Aiko Tanaka | B3: aiko_tanaka | C3: Digital-Only | D3: Japan | E3: Tokyo | F3: 28 | G3: Female | H3: aiko.tanaka@mail.jp | I3: +81-90-1234-5678 | J3: 44764 | K3: 45305 | L3: 12800 | M3: 3500.25 | N3: 810 | O3: 45000 | P3: Low | Q3: Verified | R3: 0 | S3: Active | T3: =IFERROR(M3/O3,"") -> 0.077783333 | U3: =MAX($K$2:$K$1599)-K3 -> 1 | V3: =IF(N3<670,"FAIR", IF(N3<750,"GOOD",IF(N3<800,"VERY GOOD","EXCEPTIONAL"))) -> EXCEPTIONAL | W3: =IF(F3<25,"18-24",IF(F3<35,"25-34",IF(F3<45,"35-44",IF(F3<55,"45-54","55+")))) -> 25-34 | X3: =IF(O3<=_xlfn.QUARTILE.INC($O$2:$O$1599,1),"Low",IF(O3<=_xlfn.QUARTILE.INC($O$2:$O$1599,2),"Lower-Middle",IF(O3<=_xlfn.QUARTILE.INC($O$2:$O$1599,3),"Upper-Middle","High"))) -> Low
A4: Md. Rahim Uddin | B4: rahim_uddin | C4: Business | D4: India | E4: Mumbai | F4: 35 | G4: Male | H4: rahim.uddin@business.in | I4: +91-987-654-3210 | J4: 44140 | K4: 45301 | L4: 87500.8 | M4: 45000.75 | N4: 680 | O4: 120000 | P4: Medium | Q4: Pending | R4: 0 | S4: Active | T4: =IFERROR(M4/O4,"") -> 0.37500625 | U4: =MAX($K$2:$K$1599)-K4 -> 5 | V4: =IF(N4<670,"FAIR", IF(N4<750,"GOOD",IF(N4<800,"VERY GOOD","EXCEPTIONAL"))) -> GOOD | W4: =IF(F4<25,"18-24",IF(F4<35,"25-34",IF(F4<45,"35-44",IF(F4<55,"45-54","55+")))) -> 35-44 | X4: =IF(O4<=_xlfn.QUARTILE.INC($O$2:$O$1599,1),"Low",IF(O4<=_xlfn.QUARTILE.INC($O$2:$O$1599,2),"Lower-Middle",IF(O4<=_xlfn.QUARTILE.INC($O$2:$O$1599,3),"Upper-Middle","High"))) -> Lower-Middle
A5: Anna-Louise Clarke | B5: anna_clarke | C5: Joint | D5: UK | E5: London | F5: 31 | G5: Female | H5: anna.clarke@email.co.uk | I5: +44-20-7946-0958 | J5: 44457 | K5: 45304 | L5: 25600.3 | M5: 18000 | N5: 720 | O5: 75000 | P5: Low | Q5: Verified | R5: 0 | S5: Active | T5: =IFERROR(M5/O5,"") -> 0.24 | U5: =MAX($K$2:$K$1599)-K5 -> 2 | V5: =IF(N5<670,"FAIR", IF(N5<750,"GOOD",IF(N5<800,"VERY GOOD","EXCEPTIONAL"))) -> GOOD | W5: =IF(F5<25,"18-24",IF(F5<35,"25-34",IF(F5<45,"35-44",IF(F5<55,"45-54","55+")))) -> 25-34 | X5: =IF(O5<=_xlfn.QUARTILE.INC($O$2:$O$1599,1),"Low",IF(O5<=_xlfn.QUARTILE.INC($O$2:$O$1599,2),"Lower-Middle",IF(O5<=_xlfn.QUARTILE.INC($O$2:$O$1599,3),"Upper-Middle","High"))) -> Lower-Middle
A6: John 'Jack' Thompson | B6: jack_thompson | C6: Savings | D6: US | E6: Chicago | F6: 45 | G6: Male | H6: jack.thompson@email.com | I6: +1-312-555-0123 | J6: 43250 | K6: 45302 | L6: 67500.45 | M6: 25000.8 | N6: 695 | O6: 95000 | P6: Medium | Q6: Verified | R6: 0 | S6: Active | T6: =IFERROR(M6/O6,"") -> 0.26316632 | U6: =MAX($K$2:$K$1599)-K6 -> 4 | V6: =IF(N6<670,"FAIR", IF(N6<750,"GOOD",IF(N6<800,"VERY GOOD","EXCEPTIONAL"))) -> GOOD | W6: =IF(F6<25,"18-24",IF(F6<35,"25-34",IF(F6<45,"35-44",IF(F6<55,"45-54","55+")))) -> 45-54 | X6: =IF(O6<=_xlfn.QUARTILE.INC($O$2:$O$1599,1),"Low",IF(O6<=_xlfn.QUARTILE.INC($O$2:$O$1599,2),"Lower-Middle",IF(O6<=_xlfn.QUARTILE.INC($O$2:$O$1599,3),"Upper-Middle","High"))) -> Lower-Middle
A7: Wei Zhang | B7: wei_zhang95 | C7: Current | D7: China | E7: Shanghai | F7: 26 | G7: Male | H7: wei.zhang@mail.cn | I7: +86-138-0013-8000 | J7: 44971 | K7: 45306 | L7: 9800.25 | M7: 4200.5 | N7: 780 | O7: 38000 | P7: Low | Q7: Verified | R7: 0 | S7: Active | T7: =IFERROR(M7/O7,"") -> 0.11053947 | U7: =MAX($K$2:$K$1599)-K7 -> 0 | V7: =IF(N7<670,"FAIR", IF(N7<750,"GOOD",IF(N7<800,"VERY GOOD","EXCEPTIONAL"))) -> VERY GOOD | W7: =IF(F7<25,"18-24",IF(F7<35,"25-34",IF(F7<45,"35-44",IF(F7<55,"45-54","55+")))) -> 25-34 | X7: =IF(O7<=_xlfn.QUARTILE.INC($O$2:$O$1599,1),"Low",IF(O7<=_xlfn.QUARTILE.INC($O$2:$O$1599,2),"Lower-Middle",IF(O7<=_xlfn.QUARTILE.INC($O$2:$O$1599,3),"Upper-Middle","High"))) -> Low
A8: Maria Silva Santos | B8: maria_silva | C8: Savings | D8: Brazil | E8: São Paulo | F8: 39 | G8: Female | H8: maria.santos@email.com.br | I8: +55-11-91234-5678 | J8: 43689 | K8: 45300 | L8: 32400.6 | M8: 15800.25 | N8: 710 | O8: 68000 | P8: Medium | Q8: Verified | R8: 0 | S8: Active | T8: =IFERROR(M8/O8,"") -> 0.23235662 | U8: =MAX($K$2:$K$1599)-K8 -> 6 | V8: =IF(N8<670,"FAIR", IF(N8<750,"GOOD",IF(N8<800,"VERY GOOD","EXCEPTIONAL"))) -> GOOD | W8: =IF(F8<25,"18-24",IF(F8<35,"25-34",IF(F8<45,"35-44",IF(F8<55,"45-54","55+")))) -> 35-44 | X8: =IF(O8<=_xlfn.QUARTILE.INC($O$2:$O$1599,1),"Low",IF(O8<=_xlfn.QUARTILE.INC($O$2:$O$1599,2),"Lower-Middle",IF(O8<=_xlfn.QUARTILE.INC($O$2:$O$1599,3),"Upper-Middle","High"))) -> Low
A9: Chiamaka Okoro | B9: chiamaka_o | C9: Digital-Only | D9: Nigeria | E9: Lagos | F9: 24 | G9: Female | H9: chiamaka.okoro@mail.ng | I9: +234-703-456-7890 | J9: 45066 | K9: 45305 | L9: 5600.75 | M9: 3200 | N9: 650 | O9: 29000 | P9: Medium | Q9: Pending | R9: 0 | S9: Active | T9: =IFERROR(M9/O9,"") -> 0.11034483 | U9: =MAX($K$2:$K$1599)-K9 -> 1 | V9: =IF(N9<670,"FAIR", IF(N9<750,"GOOD",IF(N9<800,"VERY GOOD","EXCEPTIONAL"))) -> FAIR | W9: =IF(F9<25,"18-24",IF(F9<35,"25-34",IF(F9<45,"35-44",IF(F9<55,"45-54","55+")))) -> 18-24 | X9: =IF(O9<=_xlfn.QUARTILE.INC($O$2:$O$1599,1),"Low",IF(O9<=_xlfn.QUARTILE.INC($O$2:$O$1599,2),"Lower-Middle",IF(O9<=_xlfn.QUARTILE.INC($O$2:$O$1599,3),"Upper-Middle","High"))) -> Low
A10: Hans Müller | B10: hans_muller | C10: Business | D10: Germany | E10: Berlin | F10: 52 | G10: Male | H10: hans.muller@company.de | I10: +49-170-1234567 | J10: 43072 | K10: 45299 | L10: 124500.9 | M10: 75000.4 | N10: 665 | O10: 150000 | P10: High | Q10: Verified | R10: 0 | S10: Active | T10: =IFERROR(M10/O10,"") -> 0.50000267 | U10: =MAX($K$2:$K$1599)-K10 -> 7 | V10: =IF(N10<670,"FAIR", IF(N10<750,"GOOD",IF(N10<800,"VERY GOOD","EXCEPTIONAL"))) -> FAIR | W10: =IF(F10<25,"18-24",IF(F10<35,"25-34",IF(F10<45,"35-44",IF(F10<55,"45-54","55+")))) -> 45-54 | X10: =IF(O10<=_xlfn.QUARTILE.INC($O$2:$O$1599,1),"Low",IF(O10<=_xlfn.QUARTILE.INC($O$2:$O$1599,2),"Lower-Middle",IF(O10<=_xlfn.QUARTILE.INC($O$2:$O$1599,3),"Upper-Middle","High"))) -> Upper-Middle
A11: Fatima Al Mansouri | B11: fatima_alm | C11: Joint | D11: UAE | E11: Dubai | F11: 36 | G11: Female | H11: fatima.mansouri@email.ae | I11: +971-50-345-6789 | J11: 44311 | K11: 45303 | L11: 78900.25 | M11: 32000.75 | N11: 730 | O11: 110000 | P11: Medium | Q11: Verified | R11: 0 | S11: Active | T11: =IFERROR(M11/O11,"") -> 0.29091591 | U11: =MAX($K$2:$K$1599)-K11 -> 3 | V11: =IF(N11<670,"FAIR", IF(N11<750,"GOOD",IF(N11<800,"VERY GOOD","EXCEPTIONAL"))) -> GOOD | W11: =IF(F11<25,"18-24",IF(F11<35,"25-34",IF(F11<45,"35-44",IF(F11<55,"45-54","55+")))) -> 35-44 | X11: =IF(O11<=_xlfn.QUARTILE.INC($O$2:$O$1599,1),"Low",IF(O11<=_xlfn.QUARTILE.INC($O$2:$O$1599,2),"Lower-Middle",IF(O11<=_xlfn.QUARTILE.INC($O$2:$O$1599,3),"Upper-Middle","High"))) -> Lower-Middle
A12: James Wilson-Smith | B12: james_wilson | C12: Student | D12: Canada | E12: Toronto | F12: 21 | G12: Male | H12: james.wilson@edu.ca | I12: +1-416-555-0189 | J12: 45179 | K12: 45304 | L12: 3200.5 | M12: 12500.8 | N12: 625 | O12: 22000 | P12: High | Q12: Pending | R12: 0 | S12: Active | T12: =IFERROR(M12/O12,"") -> 0.56821818 | U12: =MAX($K$2:$K$1599)-K12 -> 2 | V12: =IF(N12<670,"FAIR", IF(N12<750,"GOOD",IF(N12<800,"VERY GOOD","EXCEPTIONAL"))) -> FAIR | W12: =IF(F12<25,"18-24",IF(F12<35,"25-34",IF(F12<45,"35-44",IF(F12<55,"45-54","55+")))) -> 18-24 | X12: =IF(O12<=_xlfn.QUARTILE.INC($O$2:$O$1599,1),"Low",IF(O12<=_xlfn.QUARTILE.INC($O$2:$O$1599,2),"Lower-Middle",IF(O12<=_xlfn.QUARTILE.INC($O$2:$O$1599,3),"Upper-Middle","High"))) -> Low
A13: Yuki Nakamura | B13: yuki_nakamura | C13: Premium | D13: Japan | E13: Osaka | F13: 48 | G13: Female | H13: yuki.nakamura@mail.jp | I13: +81-80-9876-5432 | J13: 43847 | K13: 45301 | L13: 95600.4 | M13: 28000.6 | N13: 775 | O13: 125000 | P13: Low | Q13: Verified | R13: 0 | S13: Active | T13: =IFERROR(M13/O13,"") -> 0.2240048 | U13: =MAX($K$2:$K$1599)-K13 -> 5 | V13: =IF(N13<670,"FAIR", IF(N13<750,"GOOD",IF(N13<800,"VERY GOOD","EXCEPTIONAL"))) -> VERY GOOD | W13: =IF(F13<25,"18-24",IF(F13<35,"25-34",IF(F13<45,"35-44",IF(F13<55,"45-54","55+")))) -> 45-54 | X13: =IF(O13<=_xlfn.QUARTILE.INC($O$2:$O$1599,1),"Low",IF(O13<=_xlfn.QUARTILE.INC($O$2:$O$1599,2),"Lower-Middle",IF(O13<=_xlfn.QUARTILE.INC($O$2:$O$1599,3),"Upper-Middle","High"))) -> Lower-Middle
... A1599: James Wilson | B1599: j_wilson40 | C1599: Joint | D1599: Australia | E1599: Sydney | F1599: 79 | G1599: Male | H1599: james.wilson40@email.au | I1599: +61-462-345-678 | J1599: 44795 | K1599: 45301 | L1599: 126100.75 | M1599: 77400.8 | N1599: 730 | O1599: 187000 | P1599: Medium | Q1599: Verified | R1599: 0 | S1599: Active | T1599: =IFERROR(M1599/O1599,"") -> 0.41390802 | U1599: =MAX($K$2:$K$1599)-K1599 -> 5 | V1599: =IF(N1599<670,"FAIR", IF(N1599<750,"GOOD",IF(N1599<800,"VERY GOOD","EXCEPTIONAL"))) -> GOOD | W1599: =IF(F1599<25,"18-24",IF(F1599<35,"25-34",IF(F1599<45,"35-44",IF(F1599<55,"45-54","55+")))) -> 55+ | X1599: =IF(O1599<=_xlfn.QUARTILE.INC($O$2:$O$1599,1),"Low",IF(O1599<=_xlfn.QUARTILE.INC($O$2:$O$1599,2),"Lower-Middle",IF(O1599<=_xlfn.QUARTILE.INC($O$2:$O$1599,3),"Upper-Middle","High"))) -> Upper-Middle
A1600: Fatima Zahra | B1600: f_zahra40 | C1600: Digital-Only | D1600: Pakistan | E1600: Islamabad | F1600: 64 | G1600: Female | H1600: fatima.z | T1600: =IFERROR(M1600/O1600,"") | U1600: =MAX($K$2:$K$1599)-K1600 -> 45306 | V1600: =IF(N1600<670,"FAIR", IF(N1600<750,"GOOD",IF(N1600<800,"VERY GOOD","EXCEPTIONAL"))) -> FAIR | W1600: =IF(F1600<25,"18-24",IF(F1600<35,"25-34",IF(F1600<45,"35-44",IF(F1600<55,"45-54","55+")))) -> 55+ | X1600: =IF(O1600<=_xlfn.QUARTILE.INC($O$2:$O$1599,1),"Low",IF(O1600<=_xlfn.QUARTILE.INC($O$2:$O$1599,2),"Lower-Middle",IF(O1600<=_xlfn.QUARTILE.INC($O$2:$O$1599,3),"Upper-Middle","High"))) -> Low

Sheet Pivot tables
D1: Stacked bar chart | G1: bar chart | J1: 100% stacked bar
A2: Country | B2: Count of Username | D2: Account Type | E2: Average of Balance (USD) | G2: Risk Category | H2: Average of Debt Ratio | J2: Count of Username | K2: Risk Category
A3: Brazil | B3: 45 | D3: Business | E3: 179411.91 | G3: High | H3: 0.45638133 | J3: KYC Status | K3: High | L3: Low | M3: Medium | N3: Grand Total
A4: Canada | B4: 44 | D4: Current | E4: 33615.002 | G4: Low | H4: 0.22404098 | J4: Pending | K4: 127 | M4: 126 | N4: 253
A5: China | B5: 123 | D5: Digital-Only | E5: 18689.923 | G5: Medium | H5: 0.29718027 | J5: Verified | K5: 331 | L5: 470 | M5: 544 | N5: 1345
A6: Germany | B6: 44 | D6: Joint | E6: 93282.368 | G6: Grand Total | H6: 0.32129706 | J6: Grand Total | K6: 458 | L6: 470 | M6: 670 | N6: 1598
A7: India | B7: 47 | D7: Premium | E7: 287354.49
A8: Japan | B8: 167 | D8: Savings | E8: 63502.546
A9: Mexico | B9: 80 | D9: Student | E9: 3733.0028 | G9: Donut Chart
A10: Nigeria | B10: 125 | D10: Grand Total | E10: 102590.24 | G10: Risk Category | H10: Count of Username
A11: Pakistan | B11: 81 | G11: High | H11: 458 | J11: Income categories | K11: Average of Balance (USD) | L11: Average of Debt (USD) | M11: Average of Credit Score
A12: UK | B12: 45 | G12: Low | H12: 470 | J12: High | K12: 231739.5 | L12: 101834.73 | M12: 734.49749
A13: US | B13: 87 | D13: Account Type | E13: Average of Debt (USD) | G13: Medium | H13: 670 | J13: Low | K13: 14363.478 | L13: 10418.522 | M13: 683.01746
A14: Grand Total | B14: 888 | D14: Business | E14: 99184.318 | G14: Grand Total | H14: 1598 | J14: Lower-Middle | K14: 54201.747 | L14: 27113.68 | M14: 718.55528
D15: Current | E15: 13252.651 | J15: Upper-Middle | K15: 110660.41 | L15: 59627.494 | M15: 709.25187
D16: Digital-Only | E16: 10006.425 | J16: Grand Total | K16: 102590.24 | L16: 49693.315 | M16: 711.27347
A17: Risk Category | B17: Count of Username | D17: Joint | E17: 48785.47
A18: High | B18: 458 | D18: Premium | E18: 94744.638 | G18: Country | H18: Sum of Balance (USD) | J18: 100% stacked bar | P18: Total customers
A19: Low | B19: 470 | D19: Savings | E19: 37116.938 | G19: Brazil | H19: 11042139 | J19: Count of Username | K19: Risk Category | P19: Average balance
A20: Medium | B20: 670 | D20: Student | E20: 12872.976 | G20: China | H20: 21757479 | J20: Credit Score Band | K20: High | L20: Low | M20: Medium | N20: Grand Total
A21: Grand Total | B21: 1598 | D21: Grand Total | E21: 49693.315 | G21: India | H21: 8917685.7 | J21: EXCEPTIONAL | L21: 166 | N21: 166
G22: Ireland | H22: 5950817.8 | J22: FAIR | K22: 293 | M22: 44 | N22: 337
G23: Japan | H23: 14215928 | J23: GOOD | K23: 165 | L23: 174 | M23: 545 | N23: 884
A24: Account Type | B24: Average of Debt Ratio | D24: Age Group | E24: Average of Balance (USD) | G24: Mexico | H24: 14809867 | J24: VERY GOOD | L24: 130 | M24: 81 | N24: 211
A25: Business | B25: 0.48761985 | D25: 18-24 | E25: 2567.8868 | G25: Nigeria | H25: 16693354 | J25: Grand Total | K25: 458 | L25: 470 | M25: 670 | N25: 1598
A26: Current | B26: 0.1669235 | D26: 25-34 | E26: 12329.842 | G26: Pakistan | H26: 8461095.7
A27: Digital-Only | B27: 0.17341973 | D27: 35-44 | E27: 38903.229 | G27: Singapore | H27: 6953924.9
A28: Joint | B28: 0.32561246 | D28: 45-54 | E28: 74722.193 | G28: UK | H28: 7267276.8 | J28: Donut Chart
A29: Premium | B29: 0.31467581 | D29: 55+ | E29: 145984.3 | G29: Grand Total | H29: 1.1606957e+08 | J29: KYC Status | K29: Count of Username
A30: Savings | B30: 0.32906583 | D30: Grand Total | E30: 102590.24 | K30: 1
A31: Student | B31: 0.37407768 | J31: Pending | K31: 253
A32: Grand Total | B32: 0.32129706 | J32: Verified | K32: 1345
D33: Count of Username | J33: Grand Total | K33: 1599
D34: 1599
D37: Average of Balance (USD)
D38: 102590.24
D41: Average of Credit Score
D42: 711.27347
D45: Average of Debt Ratio
D46: 0.32129706
D49: Risk Category | E49: Count of Username
D50: High | E50: 0.28660826
D51: Low | E51: 0.29411765
D52: Medium | E52: 0.41927409
D53: Grand Total | E53: 1

Sheet Dashboard
A1: Global Banking Customer Risk Dashboard | N1: Total Customers | R1: Average Balance | V1: Avg Credit Score | Z1: Avg Debt Ratio | AD1: High Risk Users
N2: ='Pivot tables'!D34 -> 1599 | R2: ='Pivot tables'!D38 -> 102590.24 | V2: ='Pivot tables'!D42 -> 711.27347 | Z2: ='Pivot tables'!D46 -> 0.32129706 | AD2: ='Pivot tables'!E50 -> 0.28660826
A3: Global Banking Customer Risk Dashboard
A4: Global Banking Customer Risk Dashboard
